quadrupy/__init__.py
quadrupy/core.py
quadrupy-1.0.1.dist-info/licenses/LICENSE
quadrupy-1.0.1.dist-info/METADATA
quadrupy-1.0.1.dist-info/WHEEL
quadrupy-1.0.1.dist-info/top_level.txt
quadrupy-1.0.1.dist-info/RECORD
