Metadata-Version: 2.4
Name: Quadrupy
Version: 1.0.1
Summary: Simple library to control the STQ V1 via Bluetooth LE
Author-email: Jaden Stout-Reason <jadenstoutreason@gmail.com>
License: Proprietary
Project-URL: Homepage, https://github.com/JadenStout/Quadrupy
Keywords: quadruped
Classifier: Programming Language :: Python :: 3
Classifier: License :: Other/Proprietary License
Classifier: Operating System :: OS Independent
Requires-Python: >=2.00
License-File: LICENSE
Requires-Dist: pyserial
Dynamic: license-file
